sql_testing_library/__init__.py
sql_testing_library/_adapters/__init__.py
sql_testing_library/_adapters/athena.py
sql_testing_library/_adapters/base.py
sql_testing_library/_adapters/bigquery.py
sql_testing_library/_adapters/duckdb.py
sql_testing_library/_adapters/presto.py
sql_testing_library/_adapters/redshift.py
sql_testing_library/_adapters/snowflake.py
sql_testing_library/_adapters/trino.py
sql_testing_library/_core.py
sql_testing_library/_exceptions.py
sql_testing_library/_mock_table.py
sql_testing_library/_pytest_plugin.py
sql_testing_library/_sql_logger.py
sql_testing_library/_sql_utils.py
sql_testing_library/_types.py
sql_testing_library/py.typed
sql_testing_library-0.22.0.dist-info/METADATA
sql_testing_library-0.22.0.dist-info/WHEEL
sql_testing_library-0.22.0.dist-info/entry_points.txt
sql_testing_library-0.22.0.dist-info/licenses/LICENSE
sql_testing_library-0.22.0.dist-info/RECORD
