Metadata-Version: 2.4
Name: sql-testing-library
Version: 0.22.0
Summary: SQL Testing Framework for Python: Unit test SQL queries with mock data injection for BigQuery, Snowflake, Redshift, Athena, Trino, and DuckDB. Simplify data engineering ETL testing and analytics validation.
License: MIT
License-File: LICENSE
Keywords: sql,testing,unit-testing,mock-data,database-testing,bigquery,snowflake,redshift,athena,trino,duckdb,data-engineering,etl-testing,sql-validation,query-testing,pytest,data-quality,analytics-testing,sql-unit-test,database-mocking,sql-mock,data-warehouse-testing,cloud-database,aws-athena,google-bigquery,amazon-redshift,snowflake-testing,ci-cd-testing,test-automation
Author: Gurmeet Saran
Author-email: gurmeetx@gmail.com
Maintainer: Gurmeet Saran
Maintainer-email: gurmeetx@gmail.com
Requires-Python: >=3.9
Classifier: Development Status :: 4 - Beta
Classifier: Environment :: Console
Classifier: Framework :: Pytest
Classifier: Intended Audience :: Developers
Classifier: Intended Audience :: Science/Research
Classifier: Intended Audience :: System Administrators
Classifier: License :: OSI Approved :: MIT License
Classifier: Natural Language :: English
Classifier: Operating System :: OS Independent
Classifier: Programming Language :: Python :: 3
Classifier: Programming Language :: Python :: 3.9
Classifier: Programming Language :: Python :: 3.10
Classifier: Programming Language :: Python :: 3.11
Classifier: Programming Language :: Python :: 3.12
Classifier: Programming Language :: Python :: 3.13
Classifier: Programming Language :: Python :: 3.14
Classifier: Programming Language :: Python :: Implementation :: CPython
Classifier: Topic :: Database
Classifier: Topic :: Database :: Database Engines/Servers
Classifier: Topic :: Scientific/Engineering :: Information Analysis
Classifier: Topic :: Software Development :: Libraries :: Python Modules
Classifier: Topic :: Software Development :: Testing
Classifier: Topic :: Software Development :: Testing :: Unit
Classifier: Typing :: Typed
Provides-Extra: all
Provides-Extra: athena
Provides-Extra: bigquery
Provides-Extra: duckdb
Provides-Extra: redshift
Provides-Extra: snowflake
Provides-Extra: trino
Requires-Dist: db-dtypes (>=1.4.3,<2.0.0)
Requires-Dist: docutils (>=0.21.2,<0.23.0)
Requires-Dist: pandas (>=1.0.0)
Requires-Dist: pydantic (>=2.0.0)
Requires-Dist: sqlglot (>=26.0.0)
Requires-Dist: typing-extensions (>=4.5.0) ; python_version < "3.10"
Project-URL: Bug Tracker, https://github.com/gurmeetsaran/sqltesting/issues
Project-URL: Changelog, https://github.com/gurmeetsaran/sqltesting/blob/master/CHANGELOG.md
Project-URL: Contributing, https://github.com/gurmeetsaran/sqltesting/blob/master/CONTRIBUTING.md
Project-URL: Documentation, https://gurmeetsaran.github.io/sqltesting/
Project-URL: Discussions, https://github.com/gurmeetsaran/sqltesting/discussions
Project-URL: Homepage, https://gurmeetsaran.github.io/sqltesting/
Project-URL: Repository, https://github.com/gurmeetsaran/sqltesting
Project-URL: Release Notes, https://github.com/gurmeetsaran/sqltesting/releases
Project-URL: Source Code, https://github.com/gurmeetsaran/sqltesting
